loglite/__init__.py
loglite/backlog.py
loglite/cli.py
loglite/column_dict.py
loglite/config.py
loglite/database.py
loglite/errors.py
loglite/globals.py
loglite/handlers/__init__.py
loglite/handlers/insert.py
loglite/handlers/misc.py
loglite/handlers/query.py
loglite/harvesters/__init__.py
loglite/harvesters/base.py
loglite/harvesters/file.py
loglite/harvesters/manager.py
loglite/harvesters/socket.py
loglite/harvesters/zmq.py
loglite/migrations.py
loglite/server.py
loglite/tasks/__init__.py
loglite/tasks/diagnostics.py
loglite/tasks/flush_backlog.py
loglite/tasks/vacuum.py
loglite/types.py
loglite/utils.py
loglite-0.4.0.dist-info/LICENSE
loglite-0.4.0.dist-info/METADATA
loglite-0.4.0.dist-info/WHEEL
loglite-0.4.0.dist-info/entry_points.txt
loglite-0.4.0.dist-info/RECORD
