Metadata-Version: 2.1
Name: loglite
Version: 0.4.0
Summary: 
Author: namoshizun
Author-email: dilu3100@gmail.com
Requires-Python: >=3.10,<4.0
Classifier: Programming Language :: Python :: 3
Classifier: Programming Language :: Python :: 3.10
Classifier: Programming Language :: Python :: 3.11
Classifier: Programming Language :: Python :: 3.12
Classifier: Programming Language :: Python :: 3.13
Provides-Extra: zmq
Requires-Dist: aiofiles (>=25.1.0,<26.0.0)
Requires-Dist: aiohttp (>=3.13.0,<4.0.0)
Requires-Dist: aiohttp-cors (>=0.8.0,<0.9.0)
Requires-Dist: aiohttp-sse (>=2.2.0,<3.0.0)
Requires-Dist: aiosqlite (>=0.21.0,<0.22.0)
Requires-Dist: loguru (>=0.7.3,<0.8.0)
Requires-Dist: orjson (>=3.10.15,<4.0.0)
Requires-Dist: python-dotenv (>=1.0.1,<2.0.0)
Requires-Dist: pyyaml (>=6.0.2,<7.0.0)
Requires-Dist: pyzmq (>=26.0.0,<27.0.0) ; extra == "zmq"
Requires-Dist: typer (>=0.15.2,<0.16.0)
